DESCRIPTION
MANIFEST.in
README
VERSION
setup.py
kea/__init__.py
kea/cl_generator.py
kea/cli.py
kea/utils.py
kea.egg-info/PKG-INFO
kea.egg-info/SOURCES.txt
kea.egg-info/dependency_links.txt
kea.egg-info/entry_points.txt
kea.egg-info/requires.txt
kea.egg-info/top_level.txt
kea/etc/_kea.config
kea/etc/default.config
kea/etc/group.config
kea/etc/plugin.config
kea/etc/app/_emboss.config
kea/plugin/__init__.py
kea/plugin/core.py
kea/plugin/executor_pbs.py
kea/plugin/executor_simple.py
kea/plugin/filefind.py
kea/plugin/logger.py
kea/plugin/mad_provenance.py
kea/plugin/mail.py
kea/plugin/param.py
kea/plugin/register.py
kea/plugin/snippet.py
kea/plugin/cl_parser/__init__.py
kea/plugin/cl_parser/parsers/__init__.py
kea/plugin/cl_parser/parsers/bowtie2.py
kea/plugin/cl_parser/parsers/bowtie2_meta.py
kea/plugin/cl_parser/parsers/samtools.py
kea/plugin/cl_parser/parsers/samtools_meta.py
kea/plugin/cl_parser/parsers/tester.py