Metadata-Version: 1.1
Name: kea
Version: 0.0.25
Summary: Kea - make command line tools more intelligent
Home-page: https://encrypted.google.com/#q=Kea&safe=off
Author: Mark Fiers
Author-email: mark.fiers.42@gmail.com
License: UNKNOWN
Platform: UNKNOWN
Classifier: Development Status :: 4 - Beta
Classifier: Environment :: Console
Classifier: Operating System :: OS Independent
Classifier: Programming Language :: Python
Classifier: Programming Language :: Python :: 2
Classifier: Programming Language :: Python :: 2.7
